skate/__init__.py
skate/cli.py
skate/command.py
skate/command_group.py
skate/config/__init__.py
skate/config/common.py
skate/config/config.py
skate/config/config_files_initiatior.py
skate/config/config_loader.py
skate/config/yaml_parser.py
skate/core.py
skate/screens/group_picker.py
skate/screens/picker.py
skate/utils.py
peaks-0.0.2.dist-info/entry_points.txt
peaks-0.0.2.dist-info/LICENSE
peaks-0.0.2.dist-info/WHEEL
peaks-0.0.2.dist-info/METADATA
peaks-0.0.2.dist-info/RECORD
