Metadata-Version: 2.1
Name: peaks
Version: 0.0.2
Summary: Organize and run frequently used commands
Home-page: https://github.com/fpgmaas/skate
Author: Florian Maas
Author-email: fpgmaas@gmail.com
Requires-Python: >=3.8,<3.12
Classifier: Programming Language :: Python :: 3
Classifier: Programming Language :: Python :: 3.8
Classifier: Programming Language :: Python :: 3.9
Classifier: Programming Language :: Python :: 3.10
Classifier: Programming Language :: Python :: 3.11
Requires-Dist: blessed (>=1.19.1,<2.0.0)
Requires-Dist: click (>=8.1.3,<9.0.0)
Requires-Dist: pyyaml (>=6.0,<7.0)
Project-URL: Documentation, https://fpgmaas.github.io/skate/
Project-URL: Repository, https://github.com/fpgmaas/skate
